Metadata-Version: 2.1
Name: tcolour
Version: 0.1
Summary: This Modul For Set Text and background Color.
Author: Ali Crafty
Classifier: Programming Language :: Python :: 3
Classifier: Operating System :: OS Independent
Classifier: License :: OSI Approved :: MIT License
License-File: LICENSE.txt
